moduledb.py
moduledb-0.1.dist-info/LICENSE
moduledb-0.1.dist-info/WHEEL
moduledb-0.1.dist-info/METADATA
moduledb-0.1.dist-info/RECORD
