Metadata-Version: 2.1
Name: moduledb
Version: 0.1
Summary: 为 Python 模块提供数据持久化支持
Author-email: "lcctoor.com" <lcctoor@outlook.com>
Classifier: License :: OSI Approved :: Apache Software License
Requires-Dist: arts>=2023.11.26
Project-URL: HomePage, https://github.com/lcctoor/arts/tree/main/arts/moduledb
